temp_brijesh_custom_logger/__init__.py
temp_brijesh_custom_logger/logger.py
temp_brijesh_custom_logger/logging_components.py
temp_brijesh_custom_logger-4.0.0.dist-info/METADATA
temp_brijesh_custom_logger-4.0.0.dist-info/WHEEL
temp_brijesh_custom_logger-4.0.0.dist-info/top_level.txt
temp_brijesh_custom_logger-4.0.0.dist-info/RECORD
