Metadata-Version: 2.4
Name: temp_brijesh_custom_logger
Version: 4.0.0
Summary: Custom configurable logging utility
Author-email: Brijesh Turabit <brijesh.turabit@gmail.com>
Requires-Python: >=3.8
